DariasSerializer153501/__init__.py
DariasSerializer153501/canstants.py
DariasSerializer153501/main.py
DariasSerializer153501/my_serializer.py
DariasSerializer153501/serialiser_fabric.py
DariasSerializer153501/serializer_json.py
DariasSerializer153501/serializer_xml.py
DariasSerializer153501-0.1.0.dist-info/METADATA
DariasSerializer153501-0.1.0.dist-info/WHEEL
DariasSerializer153501-0.1.0.dist-info/top_level.txt
DariasSerializer153501-0.1.0.dist-info/RECORD
