Metadata-Version: 2.1
Name: DariasSerializer153501
Version: 0.1.0
Summary: Demo library
Home-page: https://dariasserializer153501.readthedocs.io/
Author: Shevtsova Daria
Author-email: dashulianorton@gmail.com
Classifier: Intended Audience :: Developers
Classifier: License :: OSI Approved :: MIT License
Classifier: Programming Language :: Python
Classifier: Programming Language :: Python :: 3
Classifier: Programming Language :: Python :: 3.6
Classifier: Programming Language :: Python :: 3.7
Classifier: Programming Language :: Python :: 3.8
Classifier: Operating System :: OS Independent
Requires-Dist: regex
